MANIFEST.in
README.md
VERSION
setup.py
aegisx.ext.iam.egg-info/PKG-INFO
aegisx.ext.iam.egg-info/SOURCES.txt
aegisx.ext.iam.egg-info/dependency_links.txt
aegisx.ext.iam.egg-info/entry_points.txt
aegisx.ext.iam.egg-info/requires.txt
aegisx.ext.iam.egg-info/top_level.txt
aegisx/ext/iam/__init__.py
aegisx/ext/iam/package.json
aegisx/ext/iam/cli/__init__.py
aegisx/ext/iam/models/__init__.py
aegisx/ext/iam/models/_anonymoussubject.py
aegisx/ext/iam/models/_authenticatedsubject.py
aegisx/ext/iam/models/_authorizationcontext.py
aegisx/ext/iam/models/_authorizedkey.py
aegisx/ext/iam/models/_authorizedkeytoken.py
aegisx/ext/iam/models/_iamattachedpolicy.py
aegisx/ext/iam/models/_iambinding.py
aegisx/ext/iam/models/_iamcondition.py
aegisx/ext/iam/models/_iampolicy.py
aegisx/ext/iam/models/_iampolicytoken.py
aegisx/ext/iam/models/_role.py
aegisx/ext/iam/models/_roledefinition.py
aegisx/ext/iam/models/_roledefinitionrequest.py
aegisx/ext/iam/models/_subject.py
aegisx/ext/iam/repository/__init__.py
aegisx/ext/iam/repository/_base.py
aegisx/ext/iam/repository/_baserole.py
aegisx/ext/iam/repository/_memory.py
aegisx/ext/iam/repository/_staticrole.py
aegisx/ext/iam/types/__init__.py
aegisx/ext/iam/types/_anonymousprincipal.py
aegisx/ext/iam/types/_authenticatedprincipal.py
aegisx/ext/iam/types/_commonexpression.py
aegisx/ext/iam/types/_domainprincipal.py
aegisx/ext/iam/types/_groupprincipal.py
aegisx/ext/iam/types/_permission.py
aegisx/ext/iam/types/_principal.py
aegisx/ext/iam/types/_rolevalidationcontext.py
aegisx/ext/iam/types/_serviceaccountprincipal.py
aegisx/ext/iam/types/_userprincipal.py
aegisx/ext/iam/types/_wildcardpermission.py