Metadata-Version: 2.4
Name: aegisx.ext.iam
Version: 0.1.0
Summary: Identity and Access Management (IAM) for Python Web Applications
Home-page: https://github.com/tensorshield/python-aegisx
Author: Immortal Izzy
Author-email: immortal.izzy@tensorshield.ai
Classifier: Development Status :: 4 - Beta
Classifier: Environment :: Web Environment
Classifier: Framework :: Pydantic :: 2
Classifier: Intended Audience :: Developers
Classifier: License :: OSI Approved :: MIT License
Classifier: Operating System :: MacOS
Classifier: Operating System :: POSIX
Classifier: Operating System :: POSIX :: Linux
Classifier: Programming Language :: Python :: 3.13
Classifier: Programming Language :: Python :: 3.14
Classifier: Programming Language :: Python :: 3 :: Only
Classifier: Topic :: Communications
Classifier: Topic :: Internet :: WWW/HTTP
Classifier: Topic :: Office/Business :: Financial
Classifier: Topic :: Security
Classifier: Topic :: Software Development :: Libraries
Requires-Dist: aegisx>=0.1.0a1
Requires-Dist: aegisx.ext.jose>=0.1.0
Requires-Dist: aegisx.ext.rfc3161>=0.0.3
Requires-Dist: cel-python
Requires-Dist: libcanonical>=0.1.2
Requires-Dist: pydantic>=2
Provides-Extra: client
Requires-Dist: httpx; extra == "client"
Provides-Extra: server
Requires-Dist: fastapi; extra == "server"
Requires-Dist: aegisx.ext.oauth[resource]; extra == "server"
Provides-Extra: develop
Requires-Dist: pytest; extra == "develop"
Requires-Dist: pytest_asyncio; extra == "develop"
Requires-Dist: coverage; extra == "develop"
Dynamic: author
Dynamic: author-email
Dynamic: classifier
Dynamic: description
Dynamic: description-content-type
Dynamic: home-page
Dynamic: provides-extra
Dynamic: requires-dist
Dynamic: summary
